LAGE.py
lage-0.1.0.dist-info/METADATA
lage-0.1.0.dist-info/WHEEL
lage-0.1.0.dist-info/top_level.txt
lage-0.1.0.dist-info/RECORD
