Metadata-Version: 2.4
Name: LAGE
Version: 0.1.0
Summary: New developer tool!
Author: ALESSANDRO FAVILLA
Requires-Python: >=3.7
Requires-Dist: pytz
Dynamic: author
Dynamic: description
Dynamic: description-content-type
Dynamic: requires-dist
Dynamic: requires-python
Dynamic: summary
